[
  {
    "users": 280,
    "CNTRYNAME": "albania"
  },
  {
    "users": 1644,
    "CNTRYNAME": "algeria"
  },
  {
    "users": 3039,
    "CNTRYNAME": "americanSamoa"
  },
  {
    "users": 24,
    "CNTRYNAME": "andorra"
  },
  {
    "users": 1252,
    "CNTRYNAME": "angola"
  },
  {
    "users": 269,
    "CNTRYNAME": "anguilla"
  },
  {
    "users": 1178,
    "CNTRYNAME": "antiguaBarbuda"
  },
  {
    "users": 30473,
    "CNTRYNAME": "argentina"
  },
  {
    "users": 89,
    "CNTRYNAME": "armenia"
  },
  {
    "users": 73,
    "CNTRYNAME": "aruba"
  },
  {
    "users": 10474,
    "CNTRYNAME": "australia"
  },
  {
    "users": 11000,
    "CNTRYNAME": "austria"
  },
  {
    "users": 58,
    "CNTRYNAME": "azerbaijan"
  },
  {
    "users": 1375,
    "CNTRYNAME": "bahamas"
  },
  {
    "users": 2,
    "CNTRYNAME": "bahrain"
  },
  {
    "users": 37494,
    "CNTRYNAME": "bangladesh"
  },
  {
    "users": 234,
    "CNTRYNAME": "barbados"
  },
  {
    "users": 16479,
    "CNTRYNAME": "belarus"
  },
  {
    "users": 4031,
    "CNTRYNAME": "belgium"
  },
  {
    "users": 961,
    "CNTRYNAME": "belize"
  },
  {
    "users": 171,
    "CNTRYNAME": "benin"
  },
  {
    "users": 5419,
    "CNTRYNAME": "bermuda"
  },
  {
    "users": 155,
    "CNTRYNAME": "bhutan"
  },
  {
    "users": 4410,
    "CNTRYNAME": "bolivia"
  },
  {
    "users": 50,
    "CNTRYNAME": "bonaireSintEustatiusSaba"
  },
  {
    "users": 16,
    "CNTRYNAME": "bosniaHerzegovina"
  },
  {
    "users": 5919,
    "CNTRYNAME": "botswana"
  },
  {
    "users": 97080,
    "CNTRYNAME": "brazil"
  },
  {
    "users": 5,
    "CNTRYNAME": "britishIndianOceanTerritory"
  },
  {
    "users": 1,
    "CNTRYNAME": "bruneiDarussalam"
  },
  {
    "users": 12135,
    "CNTRYNAME": "bulgaria"
  },
  {
    "users": 806,
    "CNTRYNAME": "burkinaFaso"
  },
  {
    "users": 6,
    "CNTRYNAME": "burundi"
  },
  {
    "users": 1541,
    "CNTRYNAME": "cambodia"
  },
  {
    "users": 73817,
    "CNTRYNAME": "cameroon"
  },
  {
    "users": 32979,
    "CNTRYNAME": "canada"
  },
  {
    "users": 7818,
    "CNTRYNAME": "capeVerde"
  },
  {
    "users": 24,
    "CNTRYNAME": "caymanIslands"
  },
  {
    "users": 13,
    "CNTRYNAME": "centralAfricanRepublic"
  },
  {
    "users": 1225,
    "CNTRYNAME": "channelIslands"
  },
  {
    "users": 942,
    "CNTRYNAME": "chile"
  },
  {
    "users": 178719,
    "CNTRYNAME": "china"
  },
  {
    "users": 1,
    "CNTRYNAME": "cocosKeeling"
  },
  {
    "users": 8468,
    "CNTRYNAME": "colombia"
  },
  {
    "users": 0,
    "CNTRYNAME": "comoros"
  },
  {
    "users": 26,
    "CNTRYNAME": "congoDR"
  },
  {
    "users": 120,
    "CNTRYNAME": "congo"
  },
  {
    "users": 14805,
    "CNTRYNAME": "costaRica"
  },
  {
    "users": 267,
    "CNTRYNAME": "croatia"
  },
  {
    "users": 138,
    "CNTRYNAME": "curacao"
  },
  {
    "users": 731,
    "CNTRYNAME": "cyprus"
  },
  {
    "users": 618,
    "CNTRYNAME": "czechia"
  },
  {
    "users": 22,
    "CNTRYNAME": "denmark"
  },
  {
    "users": 60,
    "CNTRYNAME": "djibouti"
  },
  {
    "users": 1012,
    "CNTRYNAME": "dominica"
  },
  {
    "users": 12163,
    "CNTRYNAME": "dominicanRepublic"
  },
  {
    "users": 684,
    "CNTRYNAME": "ecuador"
  },
  {
    "users": 146,
    "CNTRYNAME": "egypt"
  },
  {
    "users": 8,
    "CNTRYNAME": "equatorialGuinea"
  },
  {
    "users": 0,
    "CNTRYNAME": "eritrea"
  },
  {
    "users": 29,
    "CNTRYNAME": "estonia"
  },
  {
    "users": 49,
    "CNTRYNAME": "ethiopia"
  },
  {
    "users": 0,
    "CNTRYNAME": "faroeIslands"
  },
  {
    "users": 3919,
    "CNTRYNAME": "fijiEast"
  },
  {
    "users": 96,
    "CNTRYNAME": "finland"
  },
  {
    "users": 1286,
    "CNTRYNAME": "france"
  },
  {
    "users": 11,
    "CNTRYNAME": "frenchGuiana"
  },
  {
    "users": 5,
    "CNTRYNAME": "gabon"
  },
  {
    "users": 57,
    "CNTRYNAME": "gambia"
  },
  {
    "users": 1790,
    "CNTRYNAME": "georgia"
  },
  {
    "users": 60026,
    "CNTRYNAME": "germany"
  },
  {
    "users": 10816,
    "CNTRYNAME": "ghana"
  },
  {
    "users": 436,
    "CNTRYNAME": "greece"
  },
  {
    "users": 2,
    "CNTRYNAME": "greenland"
  },
  {
    "users": 20,
    "CNTRYNAME": "guineaBissau"
  },
  {
    "users": 77,
    "CNTRYNAME": "guinea"
  },
  {
    "users": 0,
    "CNTRYNAME": "guyana"
  },
  {
    "users": 3606,
    "CNTRYNAME": "honduras"
  },
  {
    "users": 16180,
    "CNTRYNAME": "hongKong"
  },
  {
    "users": 8762,
    "CNTRYNAME": "hungary"
  },
  {
    "users": 3,
    "CNTRYNAME": "iceland"
  },
  {
    "users": 102440,
    "CNTRYNAME": "india2020"
  },
  {
    "users": 14640,
    "CNTRYNAME": "indonesia"
  },
  {
    "users": 11074,
    "CNTRYNAME": "iran"
  },
  {
    "users": 692,
    "CNTRYNAME": "iraq"
  },
  {
    "users": 18486,
    "CNTRYNAME": "ireland"
  },
  {
    "users": 4307,
    "CNTRYNAME": "israel"
  },
  {
    "users": 2753,
    "CNTRYNAME": "italy"
  },
  {
    "users": 59922,
    "CNTRYNAME": "japan"
  },
  {
    "users": 0,
    "CNTRYNAME": "kazakhstan"
  },
  {
    "users": 1665,
    "CNTRYNAME": "kenya"
  },
  {
    "users": 5,
    "CNTRYNAME": "kuwait"
  },
  {
    "users": 1091,
    "CNTRYNAME": "kyrgyzstan"
  },
  {
    "users": 6,
    "CNTRYNAME": "laos"
  },
  {
    "users": 2843,
    "CNTRYNAME": "latvia"
  },
  {
    "users": 12,
    "CNTRYNAME": "libya"
  },
  {
    "users": 26,
    "CNTRYNAME": "liechtenstein"
  },
  {
    "users": 4697,
    "CNTRYNAME": "lithuania"
  },
  {
    "users": 2621,
    "CNTRYNAME": "luxembourg"
  },
  {
    "users": 402,
    "CNTRYNAME": "madagascarProvince"
  },
  {
    "users": 142,
    "CNTRYNAME": "mali"
  },
  {
    "users": 1091,
    "CNTRYNAME": "moldova"
  },
  {
    "users": 628,
    "CNTRYNAME": "mongolia"
  },
  {
    "users": 577,
    "CNTRYNAME": "montenegro"
  },
  {
    "users": 17,
    "CNTRYNAME": "morocco"
  },
  {
    "users": 2528,
    "CNTRYNAME": "myanmar"
  },
  {
    "users": 0,
    "CNTRYNAME": "northKorea"
  },
  {
    "users": 1842,
    "CNTRYNAME": "northMacedonia"
  },
  {
    "users": 12,
    "CNTRYNAME": "saintLucia"
  },
  {
    "users": 37399,
    "CNTRYNAME": "southKorea"
  },
  {
    "users": 27436,
    "CNTRYNAME": "spain"
  },
  {
    "users": 6239,
    "CNTRYNAME": "sriLanka"
  },
  {
    "users": 0,
    "CNTRYNAME": "stKittsNevis"
  },
  {
    "users": 14038,
    "CNTRYNAME": "switzerland"
  },
  {
    "users": 7983,
    "CNTRYNAME": "uae"
  },
  {
    "users": 39386,
    "CNTRYNAME": "uk"
  },
  {
    "users": 1057119,
    "CNTRYNAME": "wo"
  }
]