[
  {
    "users": 1421,
    "id": "CN-AH"
  },
  {
    "users": 61959,
    "id": "CN-BJ"
  },
  {
    "users": 2875,
    "id": "CN-CQ"
  },
  {
    "users": 1284,
    "id": "CN-FJ"
  },
  {
    "users": 5757,
    "id": "CN-GD"
  },
  {
    "users": 147,
    "id": "CN-GS"
  },
  {
    "users": 9,
    "id": "CN-GX"
  },
  {
    "users": 198,
    "id": "CN-GZ"
  },
  {
    "users": 795,
    "id": "CN-HA"
  },
  {
    "users": 1939,
    "id": "CN-HB"
  },
  {
    "users": 441,
    "id": "CN-HE"
  },
  {
    "users": 159,
    "id": "CN-HI"
  },
  {
    "users": 12261,
    "id": "CN-HK"
  },
  {
    "users": 188,
    "id": "CN-HL"
  },
  {
    "users": 1357,
    "id": "CN-HN"
  },
  {
    "users": 329,
    "id": "CN-JL"
  },
  {
    "users": 3216,
    "id": "CN-JS"
  },
  {
    "users": 492,
    "id": "CN-JX"
  },
  {
    "users": 804,
    "id": "CN-LN"
  },
  {
    "users": 378,
    "id": "CN-MO"
  },
  {
    "users": 1,
    "id": "CN-NM"
  },
  {
    "users": 2,
    "id": "CN-NX"
  },
  {
    "users": 19,
    "id": "CN-QH"
  },
  {
    "users": 2952,
    "id": "CN-SC"
  },
  {
    "users": 1635,
    "id": "CN-SD"
  },
  {
    "users": 46945,
    "id": "CN-SH"
  },
  {
    "users": 857,
    "id": "CN-SN"
  },
  {
    "users": 681,
    "id": "CN-SX"
  },
  {
    "users": 2251,
    "id": "CN-TJ"
  },
  {
    "users": 23895,
    "id": "CN-TW"
  },
  {
    "users": 2,
    "id": "CN-XJ"
  },
  {
    "users": 0,
    "id": "CN-XZ"
  },
  {
    "users": 375,
    "id": "CN-YN"
  },
  {
    "users": 3652,
    "id": "CN-ZJ"
  }
]