[
  {
    "users": 3588,
    "id": "CA-AB"
  },
  {
    "users": 2063,
    "id": "CA-BC"
  },
  {
    "users": 618,
    "id": "CA-MB"
  },
  {
    "users": 867,
    "id": "CA-NB"
  },
  {
    "users": 31,
    "id": "CA-NL"
  },
  {
    "users": 1072,
    "id": "CA-NS"
  },
  {
    "users": 9,
    "id": "CA-NT"
  },
  {
    "users": 13,
    "id": "CA-NU"
  },
  {
    "users": 18662,
    "id": "CA-ON"
  },
  {
    "users": 93,
    "id": "CA-PE"
  },
  {
    "users": 3978,
    "id": "CA-QC"
  },
  {
    "users": 393,
    "id": "CA-SK"
  },
  {
    "users": 83,
    "id": "CA-YT"
  }
]