[
  {
    "users": 4621,
    "id": "CA-AB"
  },
  {
    "users": 2638,
    "id": "CA-BC"
  },
  {
    "users": 790,
    "id": "CA-MB"
  },
  {
    "users": 1027,
    "id": "CA-NB"
  },
  {
    "users": 47,
    "id": "CA-NL"
  },
  {
    "users": 1374,
    "id": "CA-NS"
  },
  {
    "users": 9,
    "id": "CA-NT"
  },
  {
    "users": 16,
    "id": "CA-NU"
  },
  {
    "users": 23271,
    "id": "CA-ON"
  },
  {
    "users": 113,
    "id": "CA-PE"
  },
  {
    "users": 4819,
    "id": "CA-QC"
  },
  {
    "users": 515,
    "id": "CA-SK"
  },
  {
    "users": 101,
    "id": "CA-YT"
  }
]