[
  {
    "users": 341,
    "id": "AR-T"
  },
  {
    "users": 61,
    "id": "AR-V"
  },
  {
    "users": 1333,
    "id": "AR-D"
  },
  {
    "users": 704,
    "id": "AR-J"
  },
  {
    "users": 1377,
    "id": "AR-S"
  },
  {
    "users": 34,
    "id": "AR-G"
  },
  {
    "users": 2532,
    "id": "AR-Z"
  },
  {
    "users": 178,
    "id": "AR-A"
  },
  {
    "users": 113,
    "id": "AR-R"
  },
  {
    "users": 186,
    "id": "AR-Q"
  },
  {
    "users": 166,
    "id": "AR-N"
  },
  {
    "users": 854,
    "id": "AR-M"
  },
  {
    "users": 130,
    "id": "AR-F"
  },
  {
    "users": 43,
    "id": "AR-L"
  },
  {
    "users": 109,
    "id": "AR-Y"
  },
  {
    "users": 75,
    "id": "AR-P"
  },
  {
    "users": 206,
    "id": "AR-E"
  },
  {
    "users": 185,
    "id": "AR-W"
  },
  {
    "users": 1088,
    "id": "AR-X"
  },
  {
    "users": 491,
    "id": "AR-C"
  },
  {
    "users": 109,
    "id": "AR-U"
  },
  {
    "users": 192,
    "id": "AR-H"
  },
  {
    "users": 41,
    "id": "AR-K"
  },
  {
    "users": 13946,
    "id": "AR-B"
  }
]