[
  {
    "users": 1584,
    "id": "CN-AH"
  },
  {
    "users": 66241,
    "id": "CN-BJ"
  },
  {
    "users": 3179,
    "id": "CN-CQ"
  },
  {
    "users": 1384,
    "id": "CN-FJ"
  },
  {
    "users": 6174,
    "id": "CN-GD"
  },
  {
    "users": 159,
    "id": "CN-GS"
  },
  {
    "users": 8,
    "id": "CN-GX"
  },
  {
    "users": 232,
    "id": "CN-GZ"
  },
  {
    "users": 854,
    "id": "CN-HA"
  },
  {
    "users": 2083,
    "id": "CN-HB"
  },
  {
    "users": 500,
    "id": "CN-HE"
  },
  {
    "users": 190,
    "id": "CN-HI"
  },
  {
    "users": 14502,
    "id": "CN-HK"
  },
  {
    "users": 212,
    "id": "CN-HL"
  },
  {
    "users": 1459,
    "id": "CN-HN"
  },
  {
    "users": 356,
    "id": "CN-JL"
  },
  {
    "users": 3478,
    "id": "CN-JS"
  },
  {
    "users": 541,
    "id": "CN-JX"
  },
  {
    "users": 865,
    "id": "CN-LN"
  },
  {
    "users": 471,
    "id": "CN-MO"
  },
  {
    "users": 1,
    "id": "CN-NM"
  },
  {
    "users": 1,
    "id": "CN-NX"
  },
  {
    "users": 24,
    "id": "CN-QH"
  },
  {
    "users": 3158,
    "id": "CN-SC"
  },
  {
    "users": 1779,
    "id": "CN-SD"
  },
  {
    "users": 51322,
    "id": "CN-SH"
  },
  {
    "users": 936,
    "id": "CN-SN"
  },
  {
    "users": 732,
    "id": "CN-SX"
  },
  {
    "users": 2493,
    "id": "CN-TJ"
  },
  {
    "users": 28202,
    "id": "CN-TW"
  },
  {
    "users": 1,
    "id": "CN-XJ"
  },
  {
    "users": 0,
    "id": "CN-XZ"
  },
  {
    "users": 407,
    "id": "CN-YN"
  },
  {
    "users": 3940,
    "id": "CN-ZJ"
  }
]