[
  {
    "users": 1302,
    "id": "US-AK"
  },
  {
    "users": 2769,
    "id": "US-AL"
  },
  {
    "users": 2225,
    "id": "US-AR"
  },
  {
    "users": 9445,
    "id": "US-AZ"
  },
  {
    "users": 57487,
    "id": "US-CA"
  },
  {
    "users": 16522,
    "id": "US-CO"
  },
  {
    "users": 2534,
    "id": "US-CT"
  },
  {
    "users": 103,
    "id": "US-DC"
  },
  {
    "users": 1510,
    "id": "US-DE"
  },
  {
    "users": 23066,
    "id": "US-FL"
  },
  {
    "users": 14617,
    "id": "US-GA"
  },
  {
    "users": 1901,
    "id": "US-HI"
  },
  {
    "users": 4336,
    "id": "US-IA"
  },
  {
    "users": 3966,
    "id": "US-ID"
  },
  {
    "users": 7482,
    "id": "US-IL"
  },
  {
    "users": 6013,
    "id": "US-IN"
  },
  {
    "users": 7732,
    "id": "US-KS"
  },
  {
    "users": 2426,
    "id": "US-KY"
  },
  {
    "users": 2115,
    "id": "US-LA"
  },
  {
    "users": 6579,
    "id": "US-MA"
  },
  {
    "users": 7490,
    "id": "US-MD"
  },
  {
    "users": 2440,
    "id": "US-ME"
  },
  {
    "users": 10873,
    "id": "US-MI"
  },
  {
    "users": 6319,
    "id": "US-MN"
  },
  {
    "users": 4216,
    "id": "US-MO"
  },
  {
    "users": 811,
    "id": "US-MS"
  },
  {
    "users": 1299,
    "id": "US-MT"
  },
  {
    "users": 7884,
    "id": "US-NC"
  },
  {
    "users": 352,
    "id": "US-ND"
  },
  {
    "users": 1503,
    "id": "US-NE"
  },
  {
    "users": 1791,
    "id": "US-NH"
  },
  {
    "users": 10923,
    "id": "US-NJ"
  },
  {
    "users": 1564,
    "id": "US-NM"
  },
  {
    "users": 2332,
    "id": "US-NV"
  },
  {
    "users": 96284,
    "id": "US-NY"
  },
  {
    "users": 14829,
    "id": "US-OH"
  },
  {
    "users": 4443,
    "id": "US-OK"
  },
  {
    "users": 11348,
    "id": "US-OR"
  },
  {
    "users": 5149,
    "id": "US-PA"
  },
  {
    "users": 1303,
    "id": "US-RI"
  },
  {
    "users": 2302,
    "id": "US-SC"
  },
  {
    "users": 446,
    "id": "US-SD"
  },
  {
    "users": 3228,
    "id": "US-TN"
  },
  {
    "users": 39028,
    "id": "US-TX"
  },
  {
    "users": 10089,
    "id": "US-UT"
  },
  {
    "users": 10809,
    "id": "US-VA"
  },
  {
    "users": 1408,
    "id": "US-VT"
  },
  {
    "users": 30008,
    "id": "US-WA"
  },
  {
    "users": 4356,
    "id": "US-WI"
  },
  {
    "users": 575,
    "id": "US-WV"
  },
  {
    "users": 751,
    "id": "US-WY"
  }
]