[
  {
    "users": 309,
    "id": "DE-BB"
  },
  {
    "users": 63773,
    "id": "DE-BE"
  },
  {
    "users": 573,
    "id": "DE-BW"
  },
  {
    "users": 2650,
    "id": "DE-BY"
  },
  {
    "users": 2798,
    "id": "DE-HB"
  },
  {
    "users": 234,
    "id": "DE-HE"
  },
  {
    "users": 17401,
    "id": "DE-HH"
  },
  {
    "users": 3,
    "id": "DE-MV"
  },
  {
    "users": 357,
    "id": "DE-NI"
  },
  {
    "users": 292,
    "id": "DE-NW"
  },
  {
    "users": 59,
    "id": "DE-RP"
  },
  {
    "users": 223,
    "id": "DE-SH"
  },
  {
    "users": 401,
    "id": "DE-SL"
  },
  {
    "users": 833,
    "id": "DE-SN"
  },
  {
    "users": 43,
    "id": "DE-ST"
  },
  {
    "users": 140,
    "id": "DE-TH"
  }
]