[
  {
    "users": 408,
    "CNTRYNAME": "albania"
  },
  {
    "users": 2690,
    "CNTRYNAME": "algeria"
  },
  {
    "users": 3992,
    "CNTRYNAME": "americanSamoa"
  },
  {
    "users": 45,
    "CNTRYNAME": "andorra"
  },
  {
    "users": 2411,
    "CNTRYNAME": "angola"
  },
  {
    "users": 377,
    "CNTRYNAME": "anguilla"
  },
  {
    "users": 1626,
    "CNTRYNAME": "antiguaBarbuda"
  },
  {
    "users": 53035,
    "CNTRYNAME": "argentina"
  },
  {
    "users": 262,
    "CNTRYNAME": "armenia"
  },
  {
    "users": 112,
    "CNTRYNAME": "aruba"
  },
  {
    "users": 13224,
    "CNTRYNAME": "australia"
  },
  {
    "users": 14331,
    "CNTRYNAME": "austria"
  },
  {
    "users": 131,
    "CNTRYNAME": "azerbaijan"
  },
  {
    "users": 1833,
    "CNTRYNAME": "bahamas"
  },
  {
    "users": 4,
    "CNTRYNAME": "bahrain"
  },
  {
    "users": 63148,
    "CNTRYNAME": "bangladesh"
  },
  {
    "users": 306,
    "CNTRYNAME": "barbados"
  },
  {
    "users": 18433,
    "CNTRYNAME": "belarus"
  },
  {
    "users": 5476,
    "CNTRYNAME": "belgium"
  },
  {
    "users": 1493,
    "CNTRYNAME": "belize"
  },
  {
    "users": 324,
    "CNTRYNAME": "benin"
  },
  {
    "users": 6813,
    "CNTRYNAME": "bermuda"
  },
  {
    "users": 299,
    "CNTRYNAME": "bhutan"
  },
  {
    "users": 6180,
    "CNTRYNAME": "bolivia"
  },
  {
    "users": 102,
    "CNTRYNAME": "bonaireSintEustatiusSaba"
  },
  {
    "users": 24,
    "CNTRYNAME": "bosniaHerzegovina"
  },
  {
    "users": 8024,
    "CNTRYNAME": "botswana"
  },
  {
    "users": 173141,
    "CNTRYNAME": "brazil"
  },
  {
    "users": 16,
    "CNTRYNAME": "britishIndianOceanTerritory"
  },
  {
    "users": 2,
    "CNTRYNAME": "bruneiDarussalam"
  },
  {
    "users": 16967,
    "CNTRYNAME": "bulgaria"
  },
  {
    "users": 1226,
    "CNTRYNAME": "burkinaFaso"
  },
  {
    "users": 18,
    "CNTRYNAME": "burundi"
  },
  {
    "users": 2254,
    "CNTRYNAME": "cambodia"
  },
  {
    "users": 115289,
    "CNTRYNAME": "cameroon"
  },
  {
    "users": 42637,
    "CNTRYNAME": "canada"
  },
  {
    "users": 12999,
    "CNTRYNAME": "capeVerde"
  },
  {
    "users": 33,
    "CNTRYNAME": "caymanIslands"
  },
  {
    "users": 13,
    "CNTRYNAME": "centralAfricanRepublic"
  },
  {
    "users": 1633,
    "CNTRYNAME": "channelIslands"
  },
  {
    "users": 1417,
    "CNTRYNAME": "chile"
  },
  {
    "users": 221142,
    "CNTRYNAME": "china"
  },
  {
    "users": 7,
    "CNTRYNAME": "cocosKeeling"
  },
  {
    "users": 16054,
    "CNTRYNAME": "colombia"
  },
  {
    "users": 0,
    "CNTRYNAME": "comoros"
  },
  {
    "users": 54,
    "CNTRYNAME": "congoDR"
  },
  {
    "users": 228,
    "CNTRYNAME": "congo"
  },
  {
    "users": 17915,
    "CNTRYNAME": "costaRica"
  },
  {
    "users": 361,
    "CNTRYNAME": "croatia"
  },
  {
    "users": 184,
    "CNTRYNAME": "curacao"
  },
  {
    "users": 1589,
    "CNTRYNAME": "cyprus"
  },
  {
    "users": 864,
    "CNTRYNAME": "czechia"
  },
  {
    "users": 37,
    "CNTRYNAME": "denmark"
  },
  {
    "users": 133,
    "CNTRYNAME": "djibouti"
  },
  {
    "users": 1254,
    "CNTRYNAME": "dominica"
  },
  {
    "users": 16851,
    "CNTRYNAME": "dominicanRepublic"
  },
  {
    "users": 1095,
    "CNTRYNAME": "ecuador"
  },
  {
    "users": 371,
    "CNTRYNAME": "egypt"
  },
  {
    "users": 17,
    "CNTRYNAME": "equatorialGuinea"
  },
  {
    "users": 0,
    "CNTRYNAME": "eritrea"
  },
  {
    "users": 39,
    "CNTRYNAME": "estonia"
  },
  {
    "users": 124,
    "CNTRYNAME": "ethiopia"
  },
  {
    "users": 0,
    "CNTRYNAME": "faroeIslands"
  },
  {
    "users": 4815,
    "CNTRYNAME": "fijiEast"
  },
  {
    "users": 146,
    "CNTRYNAME": "finland"
  },
  {
    "users": 2047,
    "CNTRYNAME": "france"
  },
  {
    "users": 13,
    "CNTRYNAME": "frenchGuiana"
  },
  {
    "users": 5,
    "CNTRYNAME": "gabon"
  },
  {
    "users": 82,
    "CNTRYNAME": "gambia"
  },
  {
    "users": 4753,
    "CNTRYNAME": "georgia"
  },
  {
    "users": 77766,
    "CNTRYNAME": "germany"
  },
  {
    "users": 14518,
    "CNTRYNAME": "ghana"
  },
  {
    "users": 568,
    "CNTRYNAME": "greece"
  },
  {
    "users": 2,
    "CNTRYNAME": "greenland"
  },
  {
    "users": 38,
    "CNTRYNAME": "guineaBissau"
  },
  {
    "users": 155,
    "CNTRYNAME": "guinea"
  },
  {
    "users": 0,
    "CNTRYNAME": "guyana"
  },
  {
    "users": 4814,
    "CNTRYNAME": "honduras"
  },
  {
    "users": 22055,
    "CNTRYNAME": "hongKong"
  },
  {
    "users": 11202,
    "CNTRYNAME": "hungary"
  },
  {
    "users": 3,
    "CNTRYNAME": "iceland"
  },
  {
    "users": 177846,
    "CNTRYNAME": "india2020"
  },
  {
    "users": 24332,
    "CNTRYNAME": "indonesia"
  },
  {
    "users": 18599,
    "CNTRYNAME": "iran"
  },
  {
    "users": 1214,
    "CNTRYNAME": "iraq"
  },
  {
    "users": 22993,
    "CNTRYNAME": "ireland"
  },
  {
    "users": 6122,
    "CNTRYNAME": "israel"
  },
  {
    "users": 3995,
    "CNTRYNAME": "italy"
  },
  {
    "users": 73937,
    "CNTRYNAME": "japan"
  },
  {
    "users": 3,
    "CNTRYNAME": "kazakhstan"
  },
  {
    "users": 3197,
    "CNTRYNAME": "kenya"
  },
  {
    "users": 7,
    "CNTRYNAME": "kuwait"
  },
  {
    "users": 2551,
    "CNTRYNAME": "kyrgyzstan"
  },
  {
    "users": 18,
    "CNTRYNAME": "laos"
  },
  {
    "users": 3784,
    "CNTRYNAME": "latvia"
  },
  {
    "users": 25,
    "CNTRYNAME": "libya"
  },
  {
    "users": 31,
    "CNTRYNAME": "liechtenstein"
  },
  {
    "users": 6702,
    "CNTRYNAME": "lithuania"
  },
  {
    "users": 3645,
    "CNTRYNAME": "luxembourg"
  },
  {
    "users": 913,
    "CNTRYNAME": "madagascarProvince"
  },
  {
    "users": 273,
    "CNTRYNAME": "mali"
  },
  {
    "users": 1496,
    "CNTRYNAME": "moldova"
  },
  {
    "users": 941,
    "CNTRYNAME": "mongolia"
  },
  {
    "users": 1090,
    "CNTRYNAME": "montenegro"
  },
  {
    "users": 68,
    "CNTRYNAME": "morocco"
  },
  {
    "users": 3822,
    "CNTRYNAME": "myanmar"
  },
  {
    "users": 0,
    "CNTRYNAME": "northKorea"
  },
  {
    "users": 2560,
    "CNTRYNAME": "northMacedonia"
  },
  {
    "users": 22,
    "CNTRYNAME": "saintLucia"
  },
  {
    "users": 58890,
    "CNTRYNAME": "southKorea"
  },
  {
    "users": 37922,
    "CNTRYNAME": "spain"
  },
  {
    "users": 10521,
    "CNTRYNAME": "sriLanka"
  },
  {
    "users": 0,
    "CNTRYNAME": "stKittsNevis"
  },
  {
    "users": 18287,
    "CNTRYNAME": "switzerland"
  },
  {
    "users": 14101,
    "CNTRYNAME": "uae"
  },
  {
    "users": 50512,
    "CNTRYNAME": "uk"
  },
  {
    "users": 1544468,
    "CNTRYNAME": "wo"
  }
]