[
  {
    "users": 301,
    "CNTRYNAME": "albania"
  },
  {
    "users": 1795,
    "CNTRYNAME": "algeria"
  },
  {
    "users": 3166,
    "CNTRYNAME": "americanSamoa"
  },
  {
    "users": 27,
    "CNTRYNAME": "andorra"
  },
  {
    "users": 1401,
    "CNTRYNAME": "angola"
  },
  {
    "users": 279,
    "CNTRYNAME": "anguilla"
  },
  {
    "users": 1247,
    "CNTRYNAME": "antiguaBarbuda"
  },
  {
    "users": 33348,
    "CNTRYNAME": "argentina"
  },
  {
    "users": 98,
    "CNTRYNAME": "armenia"
  },
  {
    "users": 78,
    "CNTRYNAME": "aruba"
  },
  {
    "users": 10837,
    "CNTRYNAME": "australia"
  },
  {
    "users": 11372,
    "CNTRYNAME": "austria"
  },
  {
    "users": 68,
    "CNTRYNAME": "azerbaijan"
  },
  {
    "users": 1433,
    "CNTRYNAME": "bahamas"
  },
  {
    "users": 2,
    "CNTRYNAME": "bahrain"
  },
  {
    "users": 40696,
    "CNTRYNAME": "bangladesh"
  },
  {
    "users": 239,
    "CNTRYNAME": "barbados"
  },
  {
    "users": 17393,
    "CNTRYNAME": "belarus"
  },
  {
    "users": 4193,
    "CNTRYNAME": "belgium"
  },
  {
    "users": 1017,
    "CNTRYNAME": "belize"
  },
  {
    "users": 183,
    "CNTRYNAME": "benin"
  },
  {
    "users": 5605,
    "CNTRYNAME": "bermuda"
  },
  {
    "users": 181,
    "CNTRYNAME": "bhutan"
  },
  {
    "users": 4614,
    "CNTRYNAME": "bolivia"
  },
  {
    "users": 56,
    "CNTRYNAME": "bonaireSintEustatiusSaba"
  },
  {
    "users": 16,
    "CNTRYNAME": "bosniaHerzegovina"
  },
  {
    "users": 6182,
    "CNTRYNAME": "botswana"
  },
  {
    "users": 107148,
    "CNTRYNAME": "brazil"
  },
  {
    "users": 7,
    "CNTRYNAME": "britishIndianOceanTerritory"
  },
  {
    "users": 1,
    "CNTRYNAME": "bruneiDarussalam"
  },
  {
    "users": 12669,
    "CNTRYNAME": "bulgaria"
  },
  {
    "users": 841,
    "CNTRYNAME": "burkinaFaso"
  },
  {
    "users": 7,
    "CNTRYNAME": "burundi"
  },
  {
    "users": 1619,
    "CNTRYNAME": "cambodia"
  },
  {
    "users": 79226,
    "CNTRYNAME": "cameroon"
  },
  {
    "users": 34117,
    "CNTRYNAME": "canada"
  },
  {
    "users": 8493,
    "CNTRYNAME": "capeVerde"
  },
  {
    "users": 25,
    "CNTRYNAME": "caymanIslands"
  },
  {
    "users": 15,
    "CNTRYNAME": "centralAfricanRepublic"
  },
  {
    "users": 136,
    "CNTRYNAME": "chad"
  },
  {
    "users": 1267,
    "CNTRYNAME": "channelIslands"
  },
  {
    "users": 986,
    "CNTRYNAME": "chile"
  },
  {
    "users": 183450,
    "CNTRYNAME": "china"
  },
  {
    "users": 4,
    "CNTRYNAME": "cocosKeeling"
  },
  {
    "users": 9475,
    "CNTRYNAME": "colombia"
  },
  {
    "users": 0,
    "CNTRYNAME": "comoros"
  },
  {
    "users": 28,
    "CNTRYNAME": "congoDR"
  },
  {
    "users": 133,
    "CNTRYNAME": "congo"
  },
  {
    "users": 15205,
    "CNTRYNAME": "costaRica"
  },
  {
    "users": 275,
    "CNTRYNAME": "croatia"
  },
  {
    "users": 141,
    "CNTRYNAME": "curacao"
  },
  {
    "users": 766,
    "CNTRYNAME": "cyprus"
  },
  {
    "users": 645,
    "CNTRYNAME": "czechia"
  },
  {
    "users": 27,
    "CNTRYNAME": "denmark"
  },
  {
    "users": 70,
    "CNTRYNAME": "djibouti"
  },
  {
    "users": 1045,
    "CNTRYNAME": "dominica"
  },
  {
    "users": 12691,
    "CNTRYNAME": "dominicanRepublic"
  },
  {
    "users": 739,
    "CNTRYNAME": "ecuador"
  },
  {
    "users": 157,
    "CNTRYNAME": "egypt"
  },
  {
    "users": 2398,
    "CNTRYNAME": "elSalvador"
  },
  {
    "users": 10,
    "CNTRYNAME": "equatorialGuinea"
  },
  {
    "users": 0,
    "CNTRYNAME": "eritrea"
  },
  {
    "users": 31,
    "CNTRYNAME": "estonia"
  },
  {
    "users": 19,
    "CNTRYNAME": "eswatini"
  },
  {
    "users": 55,
    "CNTRYNAME": "ethiopia"
  },
  {
    "users": 0,
    "CNTRYNAME": "faroeIslands"
  },
  {
    "users": 4034,
    "CNTRYNAME": "fijiEast"
  },
  {
    "users": 98,
    "CNTRYNAME": "finland"
  },
  {
    "users": 1377,
    "CNTRYNAME": "france"
  },
  {
    "users": 11,
    "CNTRYNAME": "frenchGuiana"
  },
  {
    "users": 4,
    "CNTRYNAME": "gabon"
  },
  {
    "users": 61,
    "CNTRYNAME": "gambia"
  },
  {
    "users": 1931,
    "CNTRYNAME": "georgia"
  },
  {
    "users": 62047,
    "CNTRYNAME": "germany"
  },
  {
    "users": 11278,
    "CNTRYNAME": "ghana"
  },
  {
    "users": 439,
    "CNTRYNAME": "greece"
  },
  {
    "users": 2,
    "CNTRYNAME": "greenland"
  },
  {
    "users": 22,
    "CNTRYNAME": "guineaBissau"
  },
  {
    "users": 87,
    "CNTRYNAME": "guinea"
  },
  {
    "users": 0,
    "CNTRYNAME": "guyana"
  },
  {
    "users": 3785,
    "CNTRYNAME": "honduras"
  },
  {
    "users": 16944,
    "CNTRYNAME": "hongKong"
  },
  {
    "users": 9054,
    "CNTRYNAME": "hungary"
  },
  {
    "users": 3,
    "CNTRYNAME": "iceland"
  },
  {
    "users": 111268,
    "CNTRYNAME": "india2020"
  },
  {
    "users": 15888,
    "CNTRYNAME": "indonesia"
  },
  {
    "users": 12055,
    "CNTRYNAME": "iran"
  },
  {
    "users": 781,
    "CNTRYNAME": "iraq"
  },
  {
    "users": 19057,
    "CNTRYNAME": "ireland"
  },
  {
    "users": 4556,
    "CNTRYNAME": "israel"
  },
  {
    "users": 2912,
    "CNTRYNAME": "italy"
  },
  {
    "users": 61743,
    "CNTRYNAME": "japan"
  },
  {
    "users": 0,
    "CNTRYNAME": "kazakhstan"
  },
  {
    "users": 1827,
    "CNTRYNAME": "kenya"
  },
  {
    "users": 204,
    "CNTRYNAME": "kosovo"
  },
  {
    "users": 5,
    "CNTRYNAME": "kuwait"
  },
  {
    "users": 1238,
    "CNTRYNAME": "kyrgyzstan"
  },
  {
    "users": 7,
    "CNTRYNAME": "laos"
  },
  {
    "users": 2940,
    "CNTRYNAME": "latvia"
  },
  {
    "users": 16,
    "CNTRYNAME": "libya"
  },
  {
    "users": 28,
    "CNTRYNAME": "liechtenstein"
  },
  {
    "users": 4917,
    "CNTRYNAME": "lithuania"
  },
  {
    "users": 2731,
    "CNTRYNAME": "luxembourg"
  },
  {
    "users": 456,
    "CNTRYNAME": "madagascarProvince"
  },
  {
    "users": 442,
    "CNTRYNAME": "malawi"
  },
  {
    "users": 7603,
    "CNTRYNAME": "malaysia"
  },
  {
    "users": 5,
    "CNTRYNAME": "maldives"
  },
  {
    "users": 157,
    "CNTRYNAME": "mali"
  },
  {
    "users": 8570,
    "CNTRYNAME": "malta"
  },
  {
    "users": 83,
    "CNTRYNAME": "mauritania"
  },
  {
    "users": 60516,
    "CNTRYNAME": "mexico"
  },
  {
    "users": 1134,
    "CNTRYNAME": "moldova"
  },
  {
    "users": 667,
    "CNTRYNAME": "mongolia"
  },
  {
    "users": 596,
    "CNTRYNAME": "montenegro"
  },
  {
    "users": 22,
    "CNTRYNAME": "morocco"
  },
  {
    "users": 2166,
    "CNTRYNAME": "mozambique"
  },
  {
    "users": 2721,
    "CNTRYNAME": "myanmar"
  },
  {
    "users": 5,
    "CNTRYNAME": "namibia"
  },
  {
    "users": 67,
    "CNTRYNAME": "nepal"
  },
  {
    "users": 6435,
    "CNTRYNAME": "netherlands"
  },
  {
    "users": 12972,
    "CNTRYNAME": "newZealand"
  },
  {
    "users": 4644,
    "CNTRYNAME": "nicaragua"
  },
  {
    "users": 69,
    "CNTRYNAME": "niger"
  },
  {
    "users": 18910,
    "CNTRYNAME": "nigeria"
  },
  {
    "users": 0,
    "CNTRYNAME": "northKorea"
  },
  {
    "users": 1915,
    "CNTRYNAME": "northMacedonia"
  },
  {
    "users": 10260,
    "CNTRYNAME": "norway"
  },
  {
    "users": 2688,
    "CNTRYNAME": "oman"
  },
  {
    "users": 11515,
    "CNTRYNAME": "pakistan"
  },
  {
    "users": 16521,
    "CNTRYNAME": "palestine"
  },
  {
    "users": 2519,
    "CNTRYNAME": "panama"
  },
  {
    "users": 4849,
    "CNTRYNAME": "paraguay"
  },
  {
    "users": 10856,
    "CNTRYNAME": "peru"
  },
  {
    "users": 8692,
    "CNTRYNAME": "philippines"
  },
  {
    "users": 302,
    "CNTRYNAME": "poland"
  },
  {
    "users": 18037,
    "CNTRYNAME": "portugal"
  },
  {
    "users": 29119,
    "CNTRYNAME": "puertoRico"
  },
  {
    "users": 4,
    "CNTRYNAME": "qatar"
  },
  {
    "users": 8613,
    "CNTRYNAME": "romania"
  },
  {
    "users": 31811,
    "CNTRYNAME": "russia"
  },
  {
    "users": 0,
    "CNTRYNAME": "rwanda"
  },
  {
    "users": 141,
    "CNTRYNAME": "saintHelena"
  },
  {
    "users": 13,
    "CNTRYNAME": "saintLucia"
  },
  {
    "users": 6624,
    "CNTRYNAME": "saintVincent"
  },
  {
    "users": 0,
    "CNTRYNAME": "samoa"
  },
  {
    "users": 138,
    "CNTRYNAME": "sanMarino"
  },
  {
    "users": 9,
    "CNTRYNAME": "saoTomePrincipe"
  },
  {
    "users": 110,
    "CNTRYNAME": "saudiArabia"
  },
  {
    "users": 2394,
    "CNTRYNAME": "senegal"
  },
  {
    "users": 258,
    "CNTRYNAME": "serbia"
  },
  {
    "users": 1473,
    "CNTRYNAME": "seychelles"
  },
  {
    "users": 6409,
    "CNTRYNAME": "sierraLeone"
  },
  {
    "users": 1433,
    "CNTRYNAME": "singapore"
  },
  {
    "users": 1,
    "CNTRYNAME": "slovakia"
  },
  {
    "users": 2498,
    "CNTRYNAME": "slovenia"
  },
  {
    "users": 6080,
    "CNTRYNAME": "solomonIslands"
  },
  {
    "users": 18621,
    "CNTRYNAME": "somalia"
  },
  {
    "users": 2146,
    "CNTRYNAME": "southAfrica"
  },
  {
    "users": 40328,
    "CNTRYNAME": "southKorea"
  },
  {
    "users": 244,
    "CNTRYNAME": "southSudan"
  },
  {
    "users": 28582,
    "CNTRYNAME": "spain"
  },
  {
    "users": 6838,
    "CNTRYNAME": "sriLanka"
  },
  {
    "users": 0,
    "CNTRYNAME": "stKittsNevis"
  },
  {
    "users": 39,
    "CNTRYNAME": "stPierreMiquelon"
  },
  {
    "users": 12,
    "CNTRYNAME": "sudan"
  },
  {
    "users": 170,
    "CNTRYNAME": "suriname"
  },
  {
    "users": 35,
    "CNTRYNAME": "svalbard"
  },
  {
    "users": 22355,
    "CNTRYNAME": "sweden"
  },
  {
    "users": 14568,
    "CNTRYNAME": "switzerland"
  },
  {
    "users": 17,
    "CNTRYNAME": "syria"
  },
  {
    "users": 176,
    "CNTRYNAME": "tajikistan"
  },
  {
    "users": 1909,
    "CNTRYNAME": "tanzania"
  },
  {
    "users": 2480,
    "CNTRYNAME": "thailand"
  },
  {
    "users": 104,
    "CNTRYNAME": "timorLeste"
  },
  {
    "users": 65,
    "CNTRYNAME": "togo"
  },
  {
    "users": 2873,
    "CNTRYNAME": "tunisia"
  },
  {
    "users": 49101,
    "CNTRYNAME": "turkey"
  },
  {
    "users": 221,
    "CNTRYNAME": "turkmenistan"
  },
  {
    "users": 8513,
    "CNTRYNAME": "uae"
  },
  {
    "users": 40780,
    "CNTRYNAME": "uk"
  },
  {
    "users": 35533,
    "CNTRYNAME": "ukraine"
  },
  {
    "users": 354872,
    "CNTRYNAME": "usa"
  },
  {
    "users": 455,
    "CNTRYNAME": "uzbekistan"
  },
  {
    "users": 23,
    "CNTRYNAME": "vatican"
  },
  {
    "users": 3794,
    "CNTRYNAME": "venezuela"
  },
  {
    "users": 23692,
    "CNTRYNAME": "vietnam"
  },
  {
    "users": 1945166,
    "CNTRYNAME": "wo"
  },
  {
    "users": 28,
    "CNTRYNAME": "yemen"
  },
  {
    "users": 13065,
    "CNTRYNAME": "zambia"
  },
  {
    "users": 1821,
    "CNTRYNAME": "zimbabwe"
  }
]