[
  {
    "users": 257,
    "id": "AL"
  },
  {
    "users": 1437,
    "id": "DZ"
  },
  {
    "users": 2754,
    "id": "AS"
  },
  {
    "users": 21,
    "id": "AD"
  },
  {
    "users": 1010,
    "id": "AO"
  },
  {
    "users": 257,
    "id": "AI"
  },
  {
    "users": 1072,
    "id": "AG"
  },
  {
    "users": 25986,
    "id": "AR"
  },
  {
    "users": 76,
    "id": "AM"
  },
  {
    "users": 65,
    "id": "AW"
  },
  {
    "users": 9657,
    "id": "AU"
  },
  {
    "users": 10084,
    "id": "AT"
  },
  {
    "users": 47,
    "id": "AZ"
  },
  {
    "users": 1262,
    "id": "BS"
  },
  {
    "users": 2,
    "id": "BH"
  },
  {
    "users": 31535,
    "id": "BD"
  },
  {
    "users": 212,
    "id": "BB"
  },
  {
    "users": 14834,
    "id": "BY"
  },
  {
    "users": 3655,
    "id": "BE"
  },
  {
    "users": 875,
    "id": "BZ"
  },
  {
    "users": 149,
    "id": "BJ"
  },
  {
    "users": 5105,
    "id": "BM"
  },
  {
    "users": 136,
    "id": "BT"
  },
  {
    "users": 4103,
    "id": "BO"
  },
  {
    "users": 50,
    "id": "BQ"
  },
  {
    "users": 17,
    "id": "BA"
  },
  {
    "users": 5345,
    "id": "BW"
  },
  {
    "users": 80994,
    "id": "BR"
  },
  {
    "users": 3,
    "id": "IO"
  },
  {
    "users": 0,
    "id": "BN"
  },
  {
    "users": 11020,
    "id": "BG"
  },
  {
    "users": 712,
    "id": "BF"
  },
  {
    "users": 4,
    "id": "BI"
  },
  {
    "users": 1372,
    "id": "KH"
  },
  {
    "users": 65570,
    "id": "CM"
  },
  {
    "users": 30381,
    "id": "CA"
  },
  {
    "users": 6948,
    "id": "CV"
  },
  {
    "users": 24,
    "id": "KY"
  },
  {
    "users": 12,
    "id": "CF"
  },
  {
    "users": 118,
    "id": "TD"
  },
  {
    "users": 1112,
    "id": "GG"
  },
  {
    "users": 809,
    "id": "CL"
  },
  {
    "users": 168967,
    "id": "CN"
  },
  {
    "users": 2,
    "id": "CC"
  },
  {
    "users": 7011,
    "id": "CO"
  },
  {
    "users": 0,
    "id": "KM"
  },
  {
    "users": 20,
    "id": "CD"
  },
  {
    "users": 104,
    "id": "CG"
  },
  {
    "users": 14039,
    "id": "CR"
  },
  {
    "users": 245,
    "id": "HR"
  },
  {
    "users": 132,
    "id": "CW"
  },
  {
    "users": 653,
    "id": "GB"
  },
  {
    "users": 556,
    "id": "CZ"
  },
  {
    "users": 22,
    "id": "DK"
  },
  {
    "users": 48,
    "id": "DJ"
  },
  {
    "users": 950,
    "id": "DM"
  },
  {
    "users": 10946,
    "id": "DO"
  },
  {
    "users": 613,
    "id": "EC"
  },
  {
    "users": 122,
    "id": "EG"
  },
  {
    "users": 1988,
    "id": "SV"
  },
  {
    "users": 6,
    "id": "GQ"
  },
  {
    "users": 0,
    "id": "ER"
  },
  {
    "users": 30,
    "id": "EE"
  },
  {
    "users": 14,
    "id": "SZ"
  },
  {
    "users": 39,
    "id": "ET"
  },
  {
    "users": 0,
    "id": "FO"
  },
  {
    "users": 3632,
    "id": "FJ"
  },
  {
    "users": 76,
    "id": "FI"
  },
  {
    "users": 1070,
    "id": "FR"
  },
  {
    "users": 11,
    "id": "GF"
  },
  {
    "users": 5,
    "id": "GA"
  },
  {
    "users": 47,
    "id": "GM"
  },
  {
    "users": 1558,
    "id": "GE"
  },
  {
    "users": 55122,
    "id": "DE"
  },
  {
    "users": 9819,
    "id": "GH"
  },
  {
    "users": 390,
    "id": "GR"
  },
  {
    "users": 2,
    "id": "GL"
  },
  {
    "users": 20,
    "id": "GW"
  },
  {
    "users": 64,
    "id": "GN"
  },
  {
    "users": 0,
    "id": "GY"
  },
  {
    "users": 3355,
    "id": "HN"
  },
  {
    "users": 14710,
    "id": "HK"
  },
  {
    "users": 8112,
    "id": "HU"
  },
  {
    "users": 3,
    "id": "IS"
  },
  {
    "users": 86799,
    "id": "IN"
  },
  {
    "users": 12704,
    "id": "ID"
  },
  {
    "users": 9468,
    "id": "IR"
  },
  {
    "users": 585,
    "id": "IQ"
  },
  {
    "users": 17187,
    "id": "GB"
  },
  {
    "users": 3868,
    "id": "IL"
  },
  {
    "users": 2468,
    "id": "FR"
  },
  {
    "users": 55870,
    "id": "JP"
  },
  {
    "users": 0,
    "id": "KZ"
  },
  {
    "users": 1395,
    "id": "KE"
  },
  {
    "users": 170,
    "id": "XK"
  },
  {
    "users": 5,
    "id": "KW"
  },
  {
    "users": 860,
    "id": "KG"
  },
  {
    "users": 3,
    "id": "LA"
  },
  {
    "users": 2598,
    "id": "LV"
  },
  {
    "users": 12,
    "id": "LY"
  },
  {
    "users": 24,
    "id": "LI"
  },
  {
    "users": 4286,
    "id": "LT"
  },
  {
    "users": 2376,
    "id": "LU"
  },
  {
    "users": 338,
    "id": "MG"
  },
  {
    "users": 359,
    "id": "MW"
  },
  {
    "users": 6401,
    "id": "MY"
  },
  {
    "users": 5,
    "id": "MV"
  },
  {
    "users": 119,
    "id": "ML"
  },
  {
    "users": 7558,
    "id": "MT"
  },
  {
    "users": 65,
    "id": "MR"
  },
  {
    "users": 49575,
    "id": "MX"
  },
  {
    "users": 1002,
    "id": "MD"
  },
  {
    "users": 561,
    "id": "MN"
  },
  {
    "users": 515,
    "id": "ME"
  },
  {
    "users": 12,
    "id": "MA"
  },
  {
    "users": 1678,
    "id": "MZ"
  },
  {
    "users": 2328,
    "id": "MM"
  },
  {
    "users": 5,
    "id": "NA"
  },
  {
    "users": 48,
    "id": "NP"
  },
  {
    "users": 5884,
    "id": "NL"
  },
  {
    "users": 11764,
    "id": "NZ"
  },
  {
    "users": 3964,
    "id": "NI"
  },
  {
    "users": 14846,
    "id": "NG"
  },
  {
    "users": 55,
    "id": "NE"
  },
  {
    "users": 0,
    "id": "KP"
  },
  {
    "users": 1610,
    "id": "MK"
  },
  {
    "users": 9158,
    "id": "NO"
  },
  {
    "users": 2072,
    "id": "OM"
  },
  {
    "users": 9131,
    "id": "PK"
  },
  {
    "users": 14178,
    "id": "IL"
  },
  {
    "users": 2101,
    "id": "PA"
  },
  {
    "users": 4037,
    "id": "PY"
  },
  {
    "users": 8869,
    "id": "PE"
  },
  {
    "users": 7208,
    "id": "PH"
  },
  {
    "users": 240,
    "id": "PL"
  },
  {
    "users": 14973,
    "id": "PT"
  },
  {
    "users": 25222,
    "id": "PR"
  },
  {
    "users": 4,
    "id": "QA"
  },
  {
    "users": 7498,
    "id": "RO"
  },
  {
    "users": 27193,
    "id": "RU"
  },
  {
    "users": 0,
    "id": "RW"
  },
  {
    "users": 126,
    "id": "SH"
  },
  {
    "users": 11,
    "id": "LC"
  },
  {
    "users": 5948,
    "id": "VC"
  },
  {
    "users": 0,
    "id": "WS"
  },
  {
    "users": 124,
    "id": "SM"
  },
  {
    "users": 4,
    "id": "ST"
  },
  {
    "users": 73,
    "id": "SA"
  },
  {
    "users": 2058,
    "id": "SN"
  },
  {
    "users": 238,
    "id": "RS"
  },
  {
    "users": 1335,
    "id": "SC"
  },
  {
    "users": 5766,
    "id": "SL"
  },
  {
    "users": 1253,
    "id": "SG"
  },
  {
    "users": 1,
    "id": "SK"
  },
  {
    "users": 2239,
    "id": "SI"
  },
  {
    "users": 5176,
    "id": "SB"
  },
  {
    "users": 16979,
    "id": "SO"
  },
  {
    "users": 1708,
    "id": "LS"
  },
  {
    "users": 31782,
    "id": "KR"
  },
  {
    "users": 204,
    "id": "SS"
  },
  {
    "users": 24890,
    "id": "ES"
  },
  {
    "users": 5339,
    "id": "LK"
  },
  {
    "users": 0,
    "id": "KN"
  },
  {
    "users": 35,
    "id": "PM"
  },
  {
    "users": 5,
    "id": "SD"
  },
  {
    "users": 155,
    "id": "SR"
  },
  {
    "users": 25,
    "id": "SJ"
  },
  {
    "users": 19973,
    "id": "SE"
  },
  {
    "users": 12930,
    "id": "CH"
  },
  {
    "users": 12,
    "id": "SY"
  },
  {
    "users": 120,
    "id": "TJ"
  },
  {
    "users": 1485,
    "id": "TZ"
  },
  {
    "users": 2075,
    "id": "TH"
  },
  {
    "users": 84,
    "id": "ID"
  },
  {
    "users": 54,
    "id": "TG"
  },
  {
    "users": 2190,
    "id": "TN"
  },
  {
    "users": 38649,
    "id": "TR"
  },
  {
    "users": 197,
    "id": "TM"
  },
  {
    "users": 7077,
    "id": "AE"
  },
  {
    "users": 36299,
    "id": "GB"
  },
  {
    "users": 30121,
    "id": "UA"
  },
  {
    "users": 320907,
    "id": "US"
  },
  {
    "users": 180,
    "id": "TJ"
  },
  {
    "users": 17,
    "id": "VA"
  },
  {
    "users": 3154,
    "id": "AW"
  },
  {
    "users": 18864,
    "id": "VN"
  },
  {
    "users": 19,
    "id": "YE"
  },
  {
    "users": 11380,
    "id": "ZM"
  },
  {
    "users": 1507,
    "id": "ZW"
  }
]