[
  {
    "users": 20,
    "id": "SN-ZG"
  },
  {
    "users": 6,
    "id": "SN-KD"
  },
  {
    "users": 2,
    "id": "SN-SE"
  },
  {
    "users": 1,
    "id": "SN-KE"
  },
  {
    "users": 3,
    "id": "SN-MT"
  },
  {
    "users": 1908,
    "id": "SN-SL"
  },
  {
    "users": 4,
    "id": "SN-LG"
  },
  {
    "users": 0,
    "id": "SN-KA"
  },
  {
    "users": 8,
    "id": "SN-KL"
  },
  {
    "users": 6,
    "id": "SN-DB"
  },
  {
    "users": 2,
    "id": "SN-FK"
  },
  {
    "users": 86,
    "id": "SN-TH"
  },
  {
    "users": 1979,
    "id": "SN-DK"
  },
  {
    "users": 5,
    "id": "SN-TC"
  }
]