[
      {
        "users": 1,
        "id": "CM-AD"
      },
      {
        "users": 364,
        "id": "CM-CE"
      },
      {
        "users": 12,
        "id": "CM-EN"
      },
      {
        "users": 5096,
        "id": "CM-ES"
      },
      {
        "users": 9,
        "id": "CM-LT"
      },
      {
        "users": 10198,
        "id": "CM-NO"
      },
      {
        "users": 1,
        "id": "CM-NW"
      },
      {
        "users": 10293,
        "id": "CM-OU"
      },
      {
        "users": 34245,
        "id": "CM-SU"
      },
      {
        "users": 319,
        "id": "CM-SW"
    }
]