[
  {
    "users": 871,
    "id": "US-AK"
  },
  {
    "users": 1850,
    "id": "US-AL"
  },
  {
    "users": 1451,
    "id": "US-AR"
  },
  {
    "users": 6170,
    "id": "US-AZ"
  },
  {
    "users": 39420,
    "id": "US-CA"
  },
  {
    "users": 11644,
    "id": "US-CO"
  },
  {
    "users": 1739,
    "id": "US-CT"
  },
  {
    "users": 79,
    "id": "US-DC"
  },
  {
    "users": 955,
    "id": "US-DE"
  },
  {
    "users": 14973,
    "id": "US-FL"
  },
  {
    "users": 6783,
    "id": "US-GA"
  },
  {
    "users": 1323,
    "id": "US-HI"
  },
  {
    "users": 3111,
    "id": "US-IA"
  },
  {
    "users": 2111,
    "id": "US-ID"
  },
  {
    "users": 5060,
    "id": "US-IL"
  },
  {
    "users": 4171,
    "id": "US-IN"
  },
  {
    "users": 5781,
    "id": "US-KS"
  },
  {
    "users": 1606,
    "id": "US-KY"
  },
  {
    "users": 1385,
    "id": "US-LA"
  },
  {
    "users": 4503,
    "id": "US-MA"
  },
  {
    "users": 5132,
    "id": "US-MD"
  },
  {
    "users": 1659,
    "id": "US-ME"
  },
  {
    "users": 7642,
    "id": "US-MI"
  },
  {
    "users": 4481,
    "id": "US-MN"
  },
  {
    "users": 2910,
    "id": "US-MO"
  },
  {
    "users": 525,
    "id": "US-MS"
  },
  {
    "users": 853,
    "id": "US-MT"
  },
  {
    "users": 5112,
    "id": "US-NC"
  },
  {
    "users": 220,
    "id": "US-ND"
  },
  {
    "users": 1112,
    "id": "US-NE"
  },
  {
    "users": 1229,
    "id": "US-NH"
  },
  {
    "users": 7372,
    "id": "US-NJ"
  },
  {
    "users": 1058,
    "id": "US-NM"
  },
  {
    "users": 1551,
    "id": "US-NV"
  },
  {
    "users": 70506,
    "id": "US-NY"
  },
  {
    "users": 10457,
    "id": "US-OH"
  },
  {
    "users": 3009,
    "id": "US-OK"
  },
  {
    "users": 8571,
    "id": "US-OR"
  },
  {
    "users": 3497,
    "id": "US-PA"
  },
  {
    "users": 944,
    "id": "US-RI"
  },
  {
    "users": 1491,
    "id": "US-SC"
  },
  {
    "users": 272,
    "id": "US-SD"
  },
  {
    "users": 2042,
    "id": "US-TN"
  },
  {
    "users": 25521,
    "id": "US-TX"
  },
  {
    "users": 7368,
    "id": "US-UT"
  },
  {
    "users": 7531,
    "id": "US-VA"
  },
  {
    "users": 956,
    "id": "US-VT"
  },
  {
    "users": 22816,
    "id": "US-WA"
  },
  {
    "users": 3108,
    "id": "US-WI"
  },
  {
    "users": 371,
    "id": "US-WV"
  },
  {
    "users": 487,
    "id": "US-WY"
  }
]