[
  {
    "users": 1262,
    "id": "US-AK"
  },
  {
    "users": 2699,
    "id": "US-AL"
  },
  {
    "users": 2160,
    "id": "US-AR"
  },
  {
    "users": 9190,
    "id": "US-AZ"
  },
  {
    "users": 55771,
    "id": "US-CA"
  },
  {
    "users": 16137,
    "id": "US-CO"
  },
  {
    "users": 2472,
    "id": "US-CT"
  },
  {
    "users": 96,
    "id": "US-DC"
  },
  {
    "users": 1439,
    "id": "US-DE"
  },
  {
    "users": 22266,
    "id": "US-FL"
  },
  {
    "users": 13998,
    "id": "US-GA"
  },
  {
    "users": 1856,
    "id": "US-HI"
  },
  {
    "users": 4260,
    "id": "US-IA"
  },
  {
    "users": 3894,
    "id": "US-ID"
  },
  {
    "users": 7247,
    "id": "US-IL"
  },
  {
    "users": 5862,
    "id": "US-IN"
  },
  {
    "users": 7590,
    "id": "US-KS"
  },
  {
    "users": 2352,
    "id": "US-KY"
  },
  {
    "users": 2070,
    "id": "US-LA"
  },
  {
    "users": 6392,
    "id": "US-MA"
  },
  {
    "users": 7286,
    "id": "US-MD"
  },
  {
    "users": 2372,
    "id": "US-ME"
  },
  {
    "users": 10599,
    "id": "US-MI"
  },
  {
    "users": 6173,
    "id": "US-MN"
  },
  {
    "users": 4108,
    "id": "US-MO"
  },
  {
    "users": 779,
    "id": "US-MS"
  },
  {
    "users": 1274,
    "id": "US-MT"
  },
  {
    "users": 7622,
    "id": "US-NC"
  },
  {
    "users": 345,
    "id": "US-ND"
  },
  {
    "users": 1466,
    "id": "US-NE"
  },
  {
    "users": 1742,
    "id": "US-NH"
  },
  {
    "users": 10624,
    "id": "US-NJ"
  },
  {
    "users": 1527,
    "id": "US-NM"
  },
  {
    "users": 2261,
    "id": "US-NV"
  },
  {
    "users": 93554,
    "id": "US-NY"
  },
  {
    "users": 14442,
    "id": "US-OH"
  },
  {
    "users": 4301,
    "id": "US-OK"
  },
  {
    "users": 11109,
    "id": "US-OR"
  },
  {
    "users": 5010,
    "id": "US-PA"
  },
  {
    "users": 1271,
    "id": "US-RI"
  },
  {
    "users": 2218,
    "id": "US-SC"
  },
  {
    "users": 431,
    "id": "US-SD"
  },
  {
    "users": 3123,
    "id": "US-TN"
  },
  {
    "users": 37689,
    "id": "US-TX"
  },
  {
    "users": 9864,
    "id": "US-UT"
  },
  {
    "users": 10497,
    "id": "US-VA"
  },
  {
    "users": 1383,
    "id": "US-VT"
  },
  {
    "users": 29407,
    "id": "US-WA"
  },
  {
    "users": 4260,
    "id": "US-WI"
  },
  {
    "users": 548,
    "id": "US-WV"
  },
  {
    "users": 724,
    "id": "US-WY"
  }
]